LICENSE.txt
MANIFEST.in
README.md
setup.cfg
setup.py
omnimole/__init__.py
omnimole/color.py
omnimole/detect.py
omnimole/filter.py
omnimole/preprocess.py
omnimole/register.py
omnimole/segment.py
omnimole.egg-info/PKG-INFO
omnimole.egg-info/SOURCES.txt
omnimole.egg-info/dependency_links.txt
omnimole.egg-info/entry_points.txt
omnimole.egg-info/requires.txt
omnimole.egg-info/top_level.txt