Metadata-Version: 1.1
Name: omnimole
Version: 1.1.1
Summary: An image processing toolbox for skin lesion classification
Home-page: https://github.com/omniumllc/image-processing
Author: Omnium LLC
Author-email: UNKNOWN
License: MIT
Keywords: omnium mole lesion image processing
Platform: UNKNOWN
Classifier: Development Status :: 3 - Alpha
Classifier: Intended Audience :: Developers
Classifier: License :: OSI Approved :: MIT License
Classifier: Programming Language :: Python :: 2
Classifier: Programming Language :: Python :: 2.7
Classifier: Programming Language :: Python :: 3
Classifier: Programming Language :: Python :: 3.3
Classifier: Programming Language :: Python :: 3.4
Classifier: Programming Language :: Python :: 3.5
